multiplyNums/__init__.py
multiplyNums-0.1.1.dist-info/METADATA
multiplyNums-0.1.1.dist-info/WHEEL
multiplyNums-0.1.1.dist-info/top_level.txt
multiplyNums-0.1.1.dist-info/RECORD
