Metadata-Version: 2.1
Name: multiplyNums
Version: 0.1.1
Summary: This is a package to multiply 2 numbers
Author: Roshni
